odoo/addons/sale_planner_calendar/README.rst
odoo/addons/sale_planner_calendar/__init__.py
odoo/addons/sale_planner_calendar/__manifest__.py
odoo/addons/sale_planner_calendar/data/sale_planner_calendar_action_server.xml
odoo/addons/sale_planner_calendar/data/sale_planner_calendar_cron.xml
odoo/addons/sale_planner_calendar/data/sale_planner_calendar_data.xml
odoo/addons/sale_planner_calendar/i18n/ca_ES.po
odoo/addons/sale_planner_calendar/i18n/es.po
odoo/addons/sale_planner_calendar/i18n/it.po
odoo/addons/sale_planner_calendar/i18n/sale_planner_calendar.pot
odoo/addons/sale_planner_calendar/migrations/16.0.2.0.0/post-migration.py
odoo/addons/sale_planner_calendar/migrations/16.0.2.0.0/pre-migration.py
odoo/addons/sale_planner_calendar/models/__init__.py
odoo/addons/sale_planner_calendar/models/calendar_attendee.py
odoo/addons/sale_planner_calendar/models/calendar_event.py
odoo/addons/sale_planner_calendar/models/calendar_event_type.py
odoo/addons/sale_planner_calendar/models/res_config_settings.py
odoo/addons/sale_planner_calendar/models/res_partner.py
odoo/addons/sale_planner_calendar/models/res_users.py
odoo/addons/sale_planner_calendar/models/sale_order.py
odoo/addons/sale_planner_calendar/models/sale_payment_sheet.py
odoo/addons/sale_planner_calendar/models/sale_planner_calendar_issue_type.py
odoo/addons/sale_planner_calendar/models/sale_planner_calendar_summary.py
odoo/addons/sale_planner_calendar/readme/CONFIGURE.rst
odoo/addons/sale_planner_calendar/readme/CONTRIBUTORS.rst
odoo/addons/sale_planner_calendar/readme/DESCRIPTION.rst
odoo/addons/sale_planner_calendar/readme/USAGE.rst
odoo/addons/sale_planner_calendar/security/ir.model.access.csv
odoo/addons/sale_planner_calendar/security/sale_planner_calendar_security.xml
odoo/addons/sale_planner_calendar/static/description/icon.png
odoo/addons/sale_planner_calendar/static/description/index.html
odoo/addons/sale_planner_calendar/static/img/menu_entry.png
odoo_addon_sale_planner_calendar-16.0.3.0.0.2.dist-info/METADATA
odoo_addon_sale_planner_calendar-16.0.3.0.0.2.dist-info/WHEEL
odoo_addon_sale_planner_calendar-16.0.3.0.0.2.dist-info/top_level.txt
odoo_addon_sale_planner_calendar-16.0.3.0.0.2.dist-info/RECORD
